optical_dispersion_relations/__init__.py
optical_dispersion_relations/dielectric_waveguides.py
optical_dispersion_relations/drude_lorentz.py
optical_dispersion_relations/plasmon.py
optical_dispersion_relations/utilities.py
optical_dispersion_relations-0.3.0.dist-info/LICENSE.txt
optical_dispersion_relations-0.3.0.dist-info/METADATA
optical_dispersion_relations-0.3.0.dist-info/WHEEL
optical_dispersion_relations-0.3.0.dist-info/top_level.txt
optical_dispersion_relations-0.3.0.dist-info/RECORD
