Metadata-Version: 2.1
Name: optical-dispersion-relations
Version: 0.3.0
Summary: Optical Dispersion Relations
Author: George Duffett
Project-URL: Homepage, https://github.com/g-duff/optical_dispersion_relations
Project-URL: Bug Tracker, https://github.com/g-duff/optical_dispersion_relations/issues
Classifier: Programming Language :: Python :: 3
Classifier: License :: OSI Approved :: MIT License
Classifier: Operating System :: OS Independent
Requires-Python: >=3.7
License-File: LICENSE.txt
Requires-Dist: numpy (>=1.23.4)
